{
  "_fv": 24,
  "_type": "tool",
  "definition": {
    "renderType": 1,
    "texture": "old_nail_texture",
    "customModelName": "old_nail_model:default",
    "name": "Old Nail",
    "specialInfo": [],
    "creativeTab": {
      "value": "CUSTOM:HollowKnightTab"
    },
    "toolType": "Sword",
    "harvestLevel": 1,
    "efficiency": 4.0,
    "attackSpeed": 3.0,
    "enchantability": 2,
    "damageVsEntity": 4.0,
    "usageCount": 100,
    "blocksAffected": [],
    "hasGlow": false,
    "repairItems": [],
    "immuneToFire": false,
    "stayInGridWhenCrafting": false,
    "damageOnCrafting": false
  }
}